<?xml version="1.0"?>
<nodes>
	<node>
		<text>data</text>
		<id>src/data</id>
		<cls>folder</cls>
		<leaf/>
	</node>
	<node>
		<text>Layer.js</text>
		<id>src/Layer.js</id>
		<cls>file</cls>
		<leaf>1</leaf>
	</node>
	<node>
		<text>layout</text>
		<id>src/layout</id>
		<cls>folder</cls>
		<leaf/>
	</node>
	<node>
		<text>core</text>
		<id>src/core</id>
		<cls>folder</cls>
		<leaf/>
	</node>
	<node>
		<text>Component.js</text>
		<id>src/Component.js</id>
		<cls>file</cls>
		<leaf>1</leaf>
	</node>
	<node>
		<text>flash</text>
		<id>src/flash</id>
		<cls>folder</cls>
		<leaf/>
	</node>
	<node>
		<text>chart</text>
		<id>src/chart</id>
		<cls>folder</cls>
		<leaf/>
	</node>
	<node>
		<text>Template.js</text>
		<id>src/Template.js</id>
		<cls>file</cls>
		<leaf>1</leaf>
	</node>
	<node>
		<text>LoadMask.js</text>
		<id>src/LoadMask.js</id>
		<cls>file</cls>
		<leaf>1</leaf>
	</node>
	<node>
		<text>Shadow.js</text>
		<id>src/Shadow.js</id>
		<cls>file</cls>
		<leaf>1</leaf>
	</node>
	<node>
		<text>ComponentManager.js</text>
		<id>src/ComponentManager.js</id>
		<cls>file</cls>
		<leaf>1</leaf>
	</node>
	<node>
		<text>ShadowPool.js</text>
		<id>src/ShadowPool.js</id>
		<cls>file</cls>
		<leaf>1</leaf>
	</node>
	<node>
		<text>tab</text>
		<id>src/tab</id>
		<cls>folder</cls>
		<leaf/>
	</node>
	<node>
		<text>ComponentLoader.js</text>
		<id>src/ComponentLoader.js</id>
		<cls>file</cls>
		<leaf>1</leaf>
	</node>
	<node>
		<text>ElementLoader.js</text>
		<id>src/ElementLoader.js</id>
		<cls>file</cls>
		<leaf>1</leaf>
	</node>
	<node>
		<text>window</text>
		<id>src/window</id>
		<cls>folder</cls>
		<leaf/>
	</node>
	<node>
		<text>picker</text>
		<id>src/picker</id>
		<cls>folder</cls>
		<leaf/>
	</node>
	<node>
		<text>selection</text>
		<id>src/selection</id>
		<cls>folder</cls>
		<leaf/>
	</node>
	<node>
		<text>ComponentQuery.js</text>
		<id>src/ComponentQuery.js</id>
		<cls>file</cls>
		<leaf>1</leaf>
	</node>
	<node>
		<text>util</text>
		<id>src/util</id>
		<cls>folder</cls>
		<leaf/>
	</node>
	<node>
		<text>view</text>
		<id>src/view</id>
		<cls>folder</cls>
		<leaf/>
	</node>
	<node>
		<text>XTemplate.js</text>
		<id>src/XTemplate.js</id>
		<cls>file</cls>
		<leaf>1</leaf>
	</node>
	<node>
		<text>direct</text>
		<id>src/direct</id>
		<cls>folder</cls>
		<leaf/>
	</node>
	<node>
		<text>Img.js</text>
		<id>src/Img.js</id>
		<cls>file</cls>
		<leaf>1</leaf>
	</node>
	<node>
		<text>resizer</text>
		<id>src/resizer</id>
		<cls>folder</cls>
		<leaf/>
	</node>
	<node>
		<text>form</text>
		<id>src/form</id>
		<cls>folder</cls>
		<leaf/>
	</node>
	<node>
		<text>Ajax.js</text>
		<id>src/Ajax.js</id>
		<cls>file</cls>
		<leaf>1</leaf>
	</node>
	<node>
		<text>button</text>
		<id>src/button</id>
		<cls>folder</cls>
		<leaf/>
	</node>
	<node>
		<text>slider</text>
		<id>src/slider</id>
		<cls>folder</cls>
		<leaf/>
	</node>
	<node>
		<text>fx</text>
		<id>src/fx</id>
		<cls>folder</cls>
		<leaf/>
	</node>
	<node>
		<text>draw</text>
		<id>src/draw</id>
		<cls>folder</cls>
		<leaf/>
	</node>
	<node>
		<text>FocusManager.js</text>
		<id>src/FocusManager.js</id>
		<cls>file</cls>
		<leaf>1</leaf>
	</node>
	<node>
		<text>tree</text>
		<id>src/tree</id>
		<cls>folder</cls>
		<leaf/>
	</node>
	<node>
		<text>Editor.js</text>
		<id>src/Editor.js</id>
		<cls>file</cls>
		<leaf>1</leaf>
	</node>
	<node>
		<text>ZIndexManager.js</text>
		<id>src/ZIndexManager.js</id>
		<cls>file</cls>
		<leaf>1</leaf>
	</node>
	<node>
		<text>ModelManager.js</text>
		<id>src/ModelManager.js</id>
		<cls>file</cls>
		<leaf>1</leaf>
	</node>
	<node>
		<text>Action.js</text>
		<id>src/Action.js</id>
		<cls>file</cls>
		<leaf>1</leaf>
	</node>
	<node>
		<text>AbstractManager.js</text>
		<id>src/AbstractManager.js</id>
		<cls>file</cls>
		<leaf>1</leaf>
	</node>
	<node>
		<text>container</text>
		<id>src/container</id>
		<cls>folder</cls>
		<leaf/>
	</node>
	<node>
		<text>state</text>
		<id>src/state</id>
		<cls>folder</cls>
		<leaf/>
	</node>
	<node>
		<text>toolbar</text>
		<id>src/toolbar</id>
		<cls>folder</cls>
		<leaf/>
	</node>
	<node>
		<text>panel</text>
		<id>src/panel</id>
		<cls>folder</cls>
		<leaf/>
	</node>
	<node>
		<text>menu</text>
		<id>src/menu</id>
		<cls>folder</cls>
		<leaf/>
	</node>
	<node>
		<text>PluginManager.js</text>
		<id>src/PluginManager.js</id>
		<cls>file</cls>
		<leaf>1</leaf>
	</node>
	<node>
		<text>AbstractPlugin.js</text>
		<id>src/AbstractPlugin.js</id>
		<cls>file</cls>
		<leaf>1</leaf>
	</node>
	<node>
		<text>dd</text>
		<id>src/dd</id>
		<cls>folder</cls>
		<leaf/>
	</node>
	<node>
		<text>app</text>
		<id>src/app</id>
		<cls>folder</cls>
		<leaf/>
	</node>
	<node>
		<text>tip</text>
		<id>src/tip</id>
		<cls>folder</cls>
		<leaf/>
	</node>
	<node>
		<text>grid</text>
		<id>src/grid</id>
		<cls>folder</cls>
		<leaf/>
	</node>
	<node>
		<text>ProgressBar.js</text>
		<id>src/ProgressBar.js</id>
		<cls>file</cls>
		<leaf>1</leaf>
	</node>
	<node>
		<text>AbstractComponent.js</text>
		<id>src/AbstractComponent.js</id>
		<cls>file</cls>
		<leaf>1</leaf>
	</node>
</nodes>
